{
  "mission_id": "m001-vasseur-pressure",
  "depth": 2,
  "iteration": 2,
  "current_task": "task-002",
  "current_approach": "Phase 1 — DNS Infrastructure: De Giorgi theory + computation spec",
  "approaches_tried": [
    {
      "name": "Phase 1 — DNS Infrastructure: Adapt Atlas solver + validate",
      "status": "active",
      "tasks": ["task-001", "task-002"],
      "outcome": "Solver validated (task-001). De Giorgi theory analysis in progress (task-002)."
    }
  ],
  "tasks_completed": [
    {
      "id": "task-001",
      "worker_variant": "code",
      "spec_summary": "Set up pseudospectral DNS solver on T^3, validate on Taylor-Green vortex, add pressure field computation",
      "outcome": "succeeded",
      "key_finding": "Solver validated. Pressure L^{3/2} stabilizes at Re=1000 (~3.0-3.5) while enstrophy grows to 1556. N=64 adequate for Re=100, underresolved for Re=1000."
    }
  ],
  "done": false,
  "task_budget": 15,
  "created": "2026-03-30T00:00:00Z",
  "launched_at": "2026-03-30T09:15:00Z"
}
