{
  "label": "15a1",
  "conductor": 15,
  "rank": 0,
  "sha_analytic": 1.0,
  "regulator": 1.0,
  "real_period": 2.801206084665204,
  "torsion_order": 8,
  "tamagawa_product": 8,
  "bsd_leading_coefficient": 0.3501507605831505,
  "prime_bound": 200,
  "mod_ell": 3,
  "good_primes": [
    {
      "p": 2,
      "a_p": -1,
      "reduction_type": 0,
      "p_divides_N": false,
      "frobenius_angle": -0.35355339059327373,
      "frob_trace_mod_ell": 2,
      "frob_det_mod_ell": 2,
      "frob_matrix_mod_ell": [
        [
          0,
          1
        ],
        [
          1,
          2
        ]
      ]
    },
    {
      "p": 7,
      "a_p": 0,
      "reduction_type": 0,
      "p_divides_N": false,
      "frobenius_angle": 0.0,
      "frob_trace_mod_ell": 0,
      "frob_det_mod_ell": 1,
      "frob_matrix_mod_ell": [
        [
          0,
          2
        ],
        [
          1,
          0
        ]
      ]
    },
    {
      "p": 11,
      "a_p": -4,
      "reduction_type": 0,
      "p_divides_N": false,
      "frobenius_angle": -0.6030226891555273,
      "frob_trace_mod_ell": 2,
      "frob_det_mod_ell": 2,
      "frob_matrix_mod_ell": [
        [
          0,
          1
        ],
        [
          1,
          2
        ]
      ]
    },
    {
      "p": 13,
      "a_p": -2,
      "reduction_type": 0,
      "p_divides_N": false,
      "frobenius_angle": -0.2773500981126146,
      "frob_trace_mod_ell": 1,
      "frob_det_mod_ell": 1,
      "frob_matrix_mod_ell": [
        [
          2,
          1
        ],
        [
          0,
          2
        ]
      ]
    },
    {
      "p": 17,
      "a_p": 2,
      "reduction_type": 0,
      "p_divides_N": false,
      "frobenius_angle": 0.24253562503633297,
      "frob_trace_mod_ell": 2,
      "frob_det_mod_ell": 2,
      "frob_matrix_mod_ell": [
        [
          0,
          1
        ],
        [
          1,
          2
        ]
      ]
    },
    {
      "p": 19,
      "a_p": 4,
      "reduction_type": 0,
      "p_divides_N": false,
      "frobenius_angle": 0.4588314677411235,
      "frob_trace_mod_ell": 1,
      "frob_det_mod_ell": 1,
      "frob_matrix_mod_ell": [
        [
          2,
          1
        ],
        [
          0,
          2
        ]
      ]
    },
    {
      "p": 23,
      "a_p": 0,
      "reduction_type": 0,
      "p_divides_N": false,
      "frobenius_angle": 0.0,
      "frob_trace_mod_ell": 0,
      "frob_det_mod_ell": 2,
      "frob_matrix_mod_ell": [
        [
          2,
          0
        ],
        [
          0,
          1
        ]
      ]
    },
    {
      "p": 29,
      "a_p": -2,
      "reduction_type": 0,
      "p_divides_N": false,
      "frobenius_angle": -0.18569533817705186,
      "frob_trace_mod_ell": 1,
      "frob_det_mod_ell": 2,
      "frob_matrix_mod_ell": [
        [
          0,
          1
        ],
        [
          1,
          1
        ]
      ]
    },
    {
      "p": 31,
      "a_p": 0,
      "reduction_type": 0,
      "p_divides_N": false,
      "frobenius_angle": 0.0,
      "frob_trace_mod_ell": 0,
      "frob_det_mod_ell": 1,
      "frob_matrix_mod_ell": [
        [
          0,
          2
        ],
        [
          1,
          0
        ]
      ]
    },
    {
      "p": 37,
      "a_p": -10,
      "reduction_type": 0,
      "p_divides_N": false,
      "frobenius_angle": -0.8219949365267865,
      "frob_trace_mod_ell": 2,
      "frob_det_mod_ell": 1,
      "frob_matrix_mod_ell": [
        [
          1,
          1
        ],
        [
          0,
          1
        ]
      ]
    },
    {
      "p": 41,
      "a_p": 10,
      "reduction_type": 0,
      "p_divides_N": false,
      "frobenius_angle": 0.7808688094430304,
      "frob_trace_mod_ell": 1,
      "frob_det_mod_ell": 2,
      "frob_matrix_mod_ell": [
        [
          0,
          1
        ],
        [
          1,
          1
        ]
      ]
    },
    {
      "p": 43,
      "a_p": 4,
      "reduction_type": 0,
      "p_divides_N": false,
      "frobenius_angle": 0.30499714066520933,
      "frob_trace_mod_ell": 1,
      "frob_det_mod_ell": 1,
      "frob_matrix_mod_ell": [
        [
          2,
          1
        ],
        [
          0,
          2
        ]
      ]
    },
    {
      "p": 47,
      "a_p": 8,
      "reduction_type": 0,
      "p_divides_N": false,
      "frobenius_angle": 0.5834599659915782,
      "frob_trace_mod_ell": 2,
      "frob_det_mod_ell": 2,
      "frob_matrix_mod_ell": [
        [
          0,
          1
        ],
        [
          1,
          2
        ]
      ]
    },
    {
      "p": 53,
      "a_p": -10,
      "reduction_type": 0,
      "p_divides_N": false,
      "frobenius_angle": -0.6868028197434451,
      "frob_trace_mod_ell": 2,
      "frob_det_mod_ell": 2,
      "frob_matrix_mod_ell": [
        [
          0,
          1
        ],
        [
          1,
          2
        ]
      ]
    },
    {
      "p": 59,
      "a_p": -4,
      "reduction_type": 0,
      "p_divides_N": false,
      "frobenius_angle": -0.26037782196164777,
      "frob_trace_mod_ell": 2,
      "frob_det_mod_ell": 2,
      "frob_matrix_mod_ell": [
        [
          0,
          1
        ],
        [
          1,
          2
        ]
      ]
    },
    {
      "p": 61,
      "a_p": -2,
      "reduction_type": 0,
      "p_divides_N": false,
      "frobenius_angle": -0.12803687993289598,
      "frob_trace_mod_ell": 1,
      "frob_det_mod_ell": 1,
      "frob_matrix_mod_ell": [
        [
          2,
          1
        ],
        [
          0,
          2
        ]
      ]
    },
    {
      "p": 67,
      "a_p": 12,
      "reduction_type": 0,
      "p_divides_N": false,
      "frobenius_angle": 0.7330166661378313,
      "frob_trace_mod_ell": 0,
      "frob_det_mod_ell": 1,
      "frob_matrix_mod_ell": [
        [
          0,
          2
        ],
        [
          1,
          0
        ]
      ]
    },
    {
      "p": 71,
      "a_p": -8,
      "reduction_type": 0,
      "p_divides_N": false,
      "frobenius_angle": -0.4747126632775413,
      "frob_trace_mod_ell": 1,
      "frob_det_mod_ell": 2,
      "frob_matrix_mod_ell": [
        [
          0,
          1
        ],
        [
          1,
          1
        ]
      ]
    },
    {
      "p": 73,
      "a_p": 10,
      "reduction_type": 0,
      "p_divides_N": false,
      "frobenius_angle": 0.5852057359806528,
      "frob_trace_mod_ell": 1,
      "frob_det_mod_ell": 1,
      "frob_matrix_mod_ell": [
        [
          2,
          1
        ],
        [
          0,
          2
        ]
      ]
    },
    {
      "p": 79,
      "a_p": 0,
      "reduction_type": 0,
      "p_divides_N": false,
      "frobenius_angle": 0.0,
      "frob_trace_mod_ell": 0,
      "frob_det_mod_ell": 1,
      "frob_matrix_mod_ell": [
        [
          0,
          2
        ],
        [
          1,
          0
        ]
      ]
    },
    {
      "p": 83,
      "a_p": 12,
      "reduction_type": 0,
      "p_divides_N": false,
      "frobenius_angle": 0.658585559938142,
      "frob_trace_mod_ell": 0,
      "frob_det_mod_ell": 2,
      "frob_matrix_mod_ell": [
        [
          2,
          0
        ],
        [
          0,
          1
        ]
      ]
    },
    {
      "p": 89,
      "a_p": -6,
      "reduction_type": 0,
      "p_divides_N": false,
      "frobenius_angle": -0.31799936400190804,
      "frob_trace_mod_ell": 0,
      "frob_det_mod_ell": 2,
      "frob_matrix_mod_ell": [
        [
          2,
          0
        ],
        [
          0,
          1
        ]
      ]
    },
    {
      "p": 97,
      "a_p": 2,
      "reduction_type": 0,
      "p_divides_N": false,
      "frobenius_angle": 0.10153461651336192,
      "frob_trace_mod_ell": 2,
      "frob_det_mod_ell": 1,
      "frob_matrix_mod_ell": [
        [
          1,
          1
        ],
        [
          0,
          1
        ]
      ]
    },
    {
      "p": 101,
      "a_p": 6,
      "reduction_type": 0,
      "p_divides_N": false,
      "frobenius_angle": 0.29851115706299675,
      "frob_trace_mod_ell": 0,
      "frob_det_mod_ell": 2,
      "frob_matrix_mod_ell": [
        [
          2,
          0
        ],
        [
          0,
          1
        ]
      ]
    },
    {
      "p": 103,
      "a_p": -16,
      "reduction_type": 0,
      "p_divides_N": false,
      "frobenius_angle": -0.7882634225314346,
      "frob_trace_mod_ell": 2,
      "frob_det_mod_ell": 1,
      "frob_matrix_mod_ell": [
        [
          1,
          1
        ],
        [
          0,
          1
        ]
      ]
    },
    {
      "p": 107,
      "a_p": -12,
      "reduction_type": 0,
      "p_divides_N": false,
      "frobenius_angle": -0.5800418934273981,
      "frob_trace_mod_ell": 0,
      "frob_det_mod_ell": 2,
      "frob_matrix_mod_ell": [
        [
          2,
          0
        ],
        [
          0,
          1
        ]
      ]
    },
    {
      "p": 109,
      "a_p": 14,
      "reduction_type": 0,
      "p_divides_N": false,
      "frobenius_angle": 0.6704783996548059,
      "frob_trace_mod_ell": 2,
      "frob_det_mod_ell": 1,
      "frob_matrix_mod_ell": [
        [
          1,
          1
        ],
        [
          0,
          1
        ]
      ]
    },
    {
      "p": 113,
      "a_p": 2,
      "reduction_type": 0,
      "p_divides_N": false,
      "frobenius_angle": 0.09407208683835973,
      "frob_trace_mod_ell": 2,
      "frob_det_mod_ell": 2,
      "frob_matrix_mod_ell": [
        [
          0,
          1
        ],
        [
          1,
          2
        ]
      ]
    },
    {
      "p": 127,
      "a_p": -8,
      "reduction_type": 0,
      "p_divides_N": false,
      "frobenius_angle": -0.35494260376644554,
      "frob_trace_mod_ell": 1,
      "frob_det_mod_ell": 1,
      "frob_matrix_mod_ell": [
        [
          2,
          1
        ],
        [
          0,
          2
        ]
      ]
    },
    {
      "p": 131,
      "a_p": -12,
      "reduction_type": 0,
      "p_divides_N": false,
      "frobenius_angle": -0.5242224339966227,
      "frob_trace_mod_ell": 0,
      "frob_det_mod_ell": 2,
      "frob_matrix_mod_ell": [
        [
          2,
          0
        ],
        [
          0,
          1
        ]
      ]
    },
    {
      "p": 137,
      "a_p": -6,
      "reduction_type": 0,
      "p_divides_N": false,
      "frobenius_angle": -0.25630729731502827,
      "frob_trace_mod_ell": 0,
      "frob_det_mod_ell": 2,
      "frob_matrix_mod_ell": [
        [
          2,
          0
        ],
        [
          0,
          1
        ]
      ]
    },
    {
      "p": 139,
      "a_p": -4,
      "reduction_type": 0,
      "p_divides_N": false,
      "frobenius_angle": -0.16963778593599418,
      "frob_trace_mod_ell": 2,
      "frob_det_mod_ell": 1,
      "frob_matrix_mod_ell": [
        [
          1,
          1
        ],
        [
          0,
          1
        ]
      ]
    },
    {
      "p": 149,
      "a_p": 22,
      "reduction_type": 0,
      "p_divides_N": false,
      "frobenius_angle": 0.9011551125709446,
      "frob_trace_mod_ell": 1,
      "frob_det_mod_ell": 2,
      "frob_matrix_mod_ell": [
        [
          0,
          1
        ],
        [
          1,
          1
        ]
      ]
    },
    {
      "p": 151,
      "a_p": -8,
      "reduction_type": 0,
      "p_divides_N": false,
      "frobenius_angle": -0.32551538350846376,
      "frob_trace_mod_ell": 1,
      "frob_det_mod_ell": 1,
      "frob_matrix_mod_ell": [
        [
          2,
          1
        ],
        [
          0,
          2
        ]
      ]
    },
    {
      "p": 157,
      "a_p": 14,
      "reduction_type": 0,
      "p_divides_N": false,
      "frobenius_angle": 0.5586608191273356,
      "frob_trace_mod_ell": 2,
      "frob_det_mod_ell": 1,
      "frob_matrix_mod_ell": [
        [
          1,
          1
        ],
        [
          0,
          1
        ]
      ]
    },
    {
      "p": 163,
      "a_p": -4,
      "reduction_type": 0,
      "p_divides_N": false,
      "frobenius_angle": -0.15665208999759148,
      "frob_trace_mod_ell": 2,
      "frob_det_mod_ell": 1,
      "frob_matrix_mod_ell": [
        [
          1,
          1
        ],
        [
          0,
          1
        ]
      ]
    },
    {
      "p": 167,
      "a_p": 0,
      "reduction_type": 0,
      "p_divides_N": false,
      "frobenius_angle": 0.0,
      "frob_trace_mod_ell": 0,
      "frob_det_mod_ell": 2,
      "frob_matrix_mod_ell": [
        [
          2,
          0
        ],
        [
          0,
          1
        ]
      ]
    },
    {
      "p": 173,
      "a_p": -18,
      "reduction_type": 0,
      "p_divides_N": false,
      "frobenius_angle": -0.684257329142735,
      "frob_trace_mod_ell": 0,
      "frob_det_mod_ell": 2,
      "frob_matrix_mod_ell": [
        [
          2,
          0
        ],
        [
          0,
          1
        ]
      ]
    },
    {
      "p": 179,
      "a_p": 20,
      "reduction_type": 0,
      "p_divides_N": false,
      "frobenius_angle": 0.7474350927519359,
      "frob_trace_mod_ell": 2,
      "frob_det_mod_ell": 2,
      "frob_matrix_mod_ell": [
        [
          0,
          1
        ],
        [
          1,
          2
        ]
      ]
    },
    {
      "p": 181,
      "a_p": -10,
      "reduction_type": 0,
      "p_divides_N": false,
      "frobenius_angle": -0.3716470731235832,
      "frob_trace_mod_ell": 2,
      "frob_det_mod_ell": 1,
      "frob_matrix_mod_ell": [
        [
          1,
          1
        ],
        [
          0,
          1
        ]
      ]
    },
    {
      "p": 191,
      "a_p": 16,
      "reduction_type": 0,
      "p_divides_N": false,
      "frobenius_angle": 0.5788596842339373,
      "frob_trace_mod_ell": 1,
      "frob_det_mod_ell": 2,
      "frob_matrix_mod_ell": [
        [
          0,
          1
        ],
        [
          1,
          1
        ]
      ]
    },
    {
      "p": 193,
      "a_p": 2,
      "reduction_type": 0,
      "p_divides_N": false,
      "frobenius_angle": 0.07198157507486945,
      "frob_trace_mod_ell": 2,
      "frob_det_mod_ell": 1,
      "frob_matrix_mod_ell": [
        [
          1,
          1
        ],
        [
          0,
          1
        ]
      ]
    },
    {
      "p": 197,
      "a_p": 6,
      "reduction_type": 0,
      "p_divides_N": false,
      "frobenius_angle": 0.21374114996372895,
      "frob_trace_mod_ell": 0,
      "frob_det_mod_ell": 2,
      "frob_matrix_mod_ell": [
        [
          2,
          0
        ],
        [
          0,
          1
        ]
      ]
    },
    {
      "p": 199,
      "a_p": -8,
      "reduction_type": 0,
      "p_divides_N": false,
      "frobenius_angle": -0.2835524820033343,
      "frob_trace_mod_ell": 1,
      "frob_det_mod_ell": 1,
      "frob_matrix_mod_ell": [
        [
          2,
          1
        ],
        [
          0,
          2
        ]
      ]
    }
  ],
  "bad_primes": [
    {
      "p": 3,
      "a_p": -1,
      "reduction_type": -1,
      "p_divides_N": true,
      "tamagawa_number": 2
    },
    {
      "p": 5,
      "a_p": 1,
      "reduction_type": 1,
      "p_divides_N": true,
      "tamagawa_number": 4
    }
  ],
  "all_primes": [
    {
      "p": 2,
      "a_p": -1,
      "reduction_type": 0,
      "p_divides_N": false,
      "frobenius_angle": -0.35355339059327373,
      "frob_trace_mod_ell": 2,
      "frob_det_mod_ell": 2,
      "frob_matrix_mod_ell": [
        [
          0,
          1
        ],
        [
          1,
          2
        ]
      ]
    },
    {
      "p": 3,
      "a_p": -1,
      "reduction_type": -1,
      "p_divides_N": true,
      "tamagawa_number": 2
    },
    {
      "p": 5,
      "a_p": 1,
      "reduction_type": 1,
      "p_divides_N": true,
      "tamagawa_number": 4
    },
    {
      "p": 7,
      "a_p": 0,
      "reduction_type": 0,
      "p_divides_N": false,
      "frobenius_angle": 0.0,
      "frob_trace_mod_ell": 0,
      "frob_det_mod_ell": 1,
      "frob_matrix_mod_ell": [
        [
          0,
          2
        ],
        [
          1,
          0
        ]
      ]
    },
    {
      "p": 11,
      "a_p": -4,
      "reduction_type": 0,
      "p_divides_N": false,
      "frobenius_angle": -0.6030226891555273,
      "frob_trace_mod_ell": 2,
      "frob_det_mod_ell": 2,
      "frob_matrix_mod_ell": [
        [
          0,
          1
        ],
        [
          1,
          2
        ]
      ]
    },
    {
      "p": 13,
      "a_p": -2,
      "reduction_type": 0,
      "p_divides_N": false,
      "frobenius_angle": -0.2773500981126146,
      "frob_trace_mod_ell": 1,
      "frob_det_mod_ell": 1,
      "frob_matrix_mod_ell": [
        [
          2,
          1
        ],
        [
          0,
          2
        ]
      ]
    },
    {
      "p": 17,
      "a_p": 2,
      "reduction_type": 0,
      "p_divides_N": false,
      "frobenius_angle": 0.24253562503633297,
      "frob_trace_mod_ell": 2,
      "frob_det_mod_ell": 2,
      "frob_matrix_mod_ell": [
        [
          0,
          1
        ],
        [
          1,
          2
        ]
      ]
    },
    {
      "p": 19,
      "a_p": 4,
      "reduction_type": 0,
      "p_divides_N": false,
      "frobenius_angle": 0.4588314677411235,
      "frob_trace_mod_ell": 1,
      "frob_det_mod_ell": 1,
      "frob_matrix_mod_ell": [
        [
          2,
          1
        ],
        [
          0,
          2
        ]
      ]
    },
    {
      "p": 23,
      "a_p": 0,
      "reduction_type": 0,
      "p_divides_N": false,
      "frobenius_angle": 0.0,
      "frob_trace_mod_ell": 0,
      "frob_det_mod_ell": 2,
      "frob_matrix_mod_ell": [
        [
          2,
          0
        ],
        [
          0,
          1
        ]
      ]
    },
    {
      "p": 29,
      "a_p": -2,
      "reduction_type": 0,
      "p_divides_N": false,
      "frobenius_angle": -0.18569533817705186,
      "frob_trace_mod_ell": 1,
      "frob_det_mod_ell": 2,
      "frob_matrix_mod_ell": [
        [
          0,
          1
        ],
        [
          1,
          1
        ]
      ]
    },
    {
      "p": 31,
      "a_p": 0,
      "reduction_type": 0,
      "p_divides_N": false,
      "frobenius_angle": 0.0,
      "frob_trace_mod_ell": 0,
      "frob_det_mod_ell": 1,
      "frob_matrix_mod_ell": [
        [
          0,
          2
        ],
        [
          1,
          0
        ]
      ]
    },
    {
      "p": 37,
      "a_p": -10,
      "reduction_type": 0,
      "p_divides_N": false,
      "frobenius_angle": -0.8219949365267865,
      "frob_trace_mod_ell": 2,
      "frob_det_mod_ell": 1,
      "frob_matrix_mod_ell": [
        [
          1,
          1
        ],
        [
          0,
          1
        ]
      ]
    },
    {
      "p": 41,
      "a_p": 10,
      "reduction_type": 0,
      "p_divides_N": false,
      "frobenius_angle": 0.7808688094430304,
      "frob_trace_mod_ell": 1,
      "frob_det_mod_ell": 2,
      "frob_matrix_mod_ell": [
        [
          0,
          1
        ],
        [
          1,
          1
        ]
      ]
    },
    {
      "p": 43,
      "a_p": 4,
      "reduction_type": 0,
      "p_divides_N": false,
      "frobenius_angle": 0.30499714066520933,
      "frob_trace_mod_ell": 1,
      "frob_det_mod_ell": 1,
      "frob_matrix_mod_ell": [
        [
          2,
          1
        ],
        [
          0,
          2
        ]
      ]
    },
    {
      "p": 47,
      "a_p": 8,
      "reduction_type": 0,
      "p_divides_N": false,
      "frobenius_angle": 0.5834599659915782,
      "frob_trace_mod_ell": 2,
      "frob_det_mod_ell": 2,
      "frob_matrix_mod_ell": [
        [
          0,
          1
        ],
        [
          1,
          2
        ]
      ]
    },
    {
      "p": 53,
      "a_p": -10,
      "reduction_type": 0,
      "p_divides_N": false,
      "frobenius_angle": -0.6868028197434451,
      "frob_trace_mod_ell": 2,
      "frob_det_mod_ell": 2,
      "frob_matrix_mod_ell": [
        [
          0,
          1
        ],
        [
          1,
          2
        ]
      ]
    },
    {
      "p": 59,
      "a_p": -4,
      "reduction_type": 0,
      "p_divides_N": false,
      "frobenius_angle": -0.26037782196164777,
      "frob_trace_mod_ell": 2,
      "frob_det_mod_ell": 2,
      "frob_matrix_mod_ell": [
        [
          0,
          1
        ],
        [
          1,
          2
        ]
      ]
    },
    {
      "p": 61,
      "a_p": -2,
      "reduction_type": 0,
      "p_divides_N": false,
      "frobenius_angle": -0.12803687993289598,
      "frob_trace_mod_ell": 1,
      "frob_det_mod_ell": 1,
      "frob_matrix_mod_ell": [
        [
          2,
          1
        ],
        [
          0,
          2
        ]
      ]
    },
    {
      "p": 67,
      "a_p": 12,
      "reduction_type": 0,
      "p_divides_N": false,
      "frobenius_angle": 0.7330166661378313,
      "frob_trace_mod_ell": 0,
      "frob_det_mod_ell": 1,
      "frob_matrix_mod_ell": [
        [
          0,
          2
        ],
        [
          1,
          0
        ]
      ]
    },
    {
      "p": 71,
      "a_p": -8,
      "reduction_type": 0,
      "p_divides_N": false,
      "frobenius_angle": -0.4747126632775413,
      "frob_trace_mod_ell": 1,
      "frob_det_mod_ell": 2,
      "frob_matrix_mod_ell": [
        [
          0,
          1
        ],
        [
          1,
          1
        ]
      ]
    },
    {
      "p": 73,
      "a_p": 10,
      "reduction_type": 0,
      "p_divides_N": false,
      "frobenius_angle": 0.5852057359806528,
      "frob_trace_mod_ell": 1,
      "frob_det_mod_ell": 1,
      "frob_matrix_mod_ell": [
        [
          2,
          1
        ],
        [
          0,
          2
        ]
      ]
    },
    {
      "p": 79,
      "a_p": 0,
      "reduction_type": 0,
      "p_divides_N": false,
      "frobenius_angle": 0.0,
      "frob_trace_mod_ell": 0,
      "frob_det_mod_ell": 1,
      "frob_matrix_mod_ell": [
        [
          0,
          2
        ],
        [
          1,
          0
        ]
      ]
    },
    {
      "p": 83,
      "a_p": 12,
      "reduction_type": 0,
      "p_divides_N": false,
      "frobenius_angle": 0.658585559938142,
      "frob_trace_mod_ell": 0,
      "frob_det_mod_ell": 2,
      "frob_matrix_mod_ell": [
        [
          2,
          0
        ],
        [
          0,
          1
        ]
      ]
    },
    {
      "p": 89,
      "a_p": -6,
      "reduction_type": 0,
      "p_divides_N": false,
      "frobenius_angle": -0.31799936400190804,
      "frob_trace_mod_ell": 0,
      "frob_det_mod_ell": 2,
      "frob_matrix_mod_ell": [
        [
          2,
          0
        ],
        [
          0,
          1
        ]
      ]
    },
    {
      "p": 97,
      "a_p": 2,
      "reduction_type": 0,
      "p_divides_N": false,
      "frobenius_angle": 0.10153461651336192,
      "frob_trace_mod_ell": 2,
      "frob_det_mod_ell": 1,
      "frob_matrix_mod_ell": [
        [
          1,
          1
        ],
        [
          0,
          1
        ]
      ]
    },
    {
      "p": 101,
      "a_p": 6,
      "reduction_type": 0,
      "p_divides_N": false,
      "frobenius_angle": 0.29851115706299675,
      "frob_trace_mod_ell": 0,
      "frob_det_mod_ell": 2,
      "frob_matrix_mod_ell": [
        [
          2,
          0
        ],
        [
          0,
          1
        ]
      ]
    },
    {
      "p": 103,
      "a_p": -16,
      "reduction_type": 0,
      "p_divides_N": false,
      "frobenius_angle": -0.7882634225314346,
      "frob_trace_mod_ell": 2,
      "frob_det_mod_ell": 1,
      "frob_matrix_mod_ell": [
        [
          1,
          1
        ],
        [
          0,
          1
        ]
      ]
    },
    {
      "p": 107,
      "a_p": -12,
      "reduction_type": 0,
      "p_divides_N": false,
      "frobenius_angle": -0.5800418934273981,
      "frob_trace_mod_ell": 0,
      "frob_det_mod_ell": 2,
      "frob_matrix_mod_ell": [
        [
          2,
          0
        ],
        [
          0,
          1
        ]
      ]
    },
    {
      "p": 109,
      "a_p": 14,
      "reduction_type": 0,
      "p_divides_N": false,
      "frobenius_angle": 0.6704783996548059,
      "frob_trace_mod_ell": 2,
      "frob_det_mod_ell": 1,
      "frob_matrix_mod_ell": [
        [
          1,
          1
        ],
        [
          0,
          1
        ]
      ]
    },
    {
      "p": 113,
      "a_p": 2,
      "reduction_type": 0,
      "p_divides_N": false,
      "frobenius_angle": 0.09407208683835973,
      "frob_trace_mod_ell": 2,
      "frob_det_mod_ell": 2,
      "frob_matrix_mod_ell": [
        [
          0,
          1
        ],
        [
          1,
          2
        ]
      ]
    },
    {
      "p": 127,
      "a_p": -8,
      "reduction_type": 0,
      "p_divides_N": false,
      "frobenius_angle": -0.35494260376644554,
      "frob_trace_mod_ell": 1,
      "frob_det_mod_ell": 1,
      "frob_matrix_mod_ell": [
        [
          2,
          1
        ],
        [
          0,
          2
        ]
      ]
    },
    {
      "p": 131,
      "a_p": -12,
      "reduction_type": 0,
      "p_divides_N": false,
      "frobenius_angle": -0.5242224339966227,
      "frob_trace_mod_ell": 0,
      "frob_det_mod_ell": 2,
      "frob_matrix_mod_ell": [
        [
          2,
          0
        ],
        [
          0,
          1
        ]
      ]
    },
    {
      "p": 137,
      "a_p": -6,
      "reduction_type": 0,
      "p_divides_N": false,
      "frobenius_angle": -0.25630729731502827,
      "frob_trace_mod_ell": 0,
      "frob_det_mod_ell": 2,
      "frob_matrix_mod_ell": [
        [
          2,
          0
        ],
        [
          0,
          1
        ]
      ]
    },
    {
      "p": 139,
      "a_p": -4,
      "reduction_type": 0,
      "p_divides_N": false,
      "frobenius_angle": -0.16963778593599418,
      "frob_trace_mod_ell": 2,
      "frob_det_mod_ell": 1,
      "frob_matrix_mod_ell": [
        [
          1,
          1
        ],
        [
          0,
          1
        ]
      ]
    },
    {
      "p": 149,
      "a_p": 22,
      "reduction_type": 0,
      "p_divides_N": false,
      "frobenius_angle": 0.9011551125709446,
      "frob_trace_mod_ell": 1,
      "frob_det_mod_ell": 2,
      "frob_matrix_mod_ell": [
        [
          0,
          1
        ],
        [
          1,
          1
        ]
      ]
    },
    {
      "p": 151,
      "a_p": -8,
      "reduction_type": 0,
      "p_divides_N": false,
      "frobenius_angle": -0.32551538350846376,
      "frob_trace_mod_ell": 1,
      "frob_det_mod_ell": 1,
      "frob_matrix_mod_ell": [
        [
          2,
          1
        ],
        [
          0,
          2
        ]
      ]
    },
    {
      "p": 157,
      "a_p": 14,
      "reduction_type": 0,
      "p_divides_N": false,
      "frobenius_angle": 0.5586608191273356,
      "frob_trace_mod_ell": 2,
      "frob_det_mod_ell": 1,
      "frob_matrix_mod_ell": [
        [
          1,
          1
        ],
        [
          0,
          1
        ]
      ]
    },
    {
      "p": 163,
      "a_p": -4,
      "reduction_type": 0,
      "p_divides_N": false,
      "frobenius_angle": -0.15665208999759148,
      "frob_trace_mod_ell": 2,
      "frob_det_mod_ell": 1,
      "frob_matrix_mod_ell": [
        [
          1,
          1
        ],
        [
          0,
          1
        ]
      ]
    },
    {
      "p": 167,
      "a_p": 0,
      "reduction_type": 0,
      "p_divides_N": false,
      "frobenius_angle": 0.0,
      "frob_trace_mod_ell": 0,
      "frob_det_mod_ell": 2,
      "frob_matrix_mod_ell": [
        [
          2,
          0
        ],
        [
          0,
          1
        ]
      ]
    },
    {
      "p": 173,
      "a_p": -18,
      "reduction_type": 0,
      "p_divides_N": false,
      "frobenius_angle": -0.684257329142735,
      "frob_trace_mod_ell": 0,
      "frob_det_mod_ell": 2,
      "frob_matrix_mod_ell": [
        [
          2,
          0
        ],
        [
          0,
          1
        ]
      ]
    },
    {
      "p": 179,
      "a_p": 20,
      "reduction_type": 0,
      "p_divides_N": false,
      "frobenius_angle": 0.7474350927519359,
      "frob_trace_mod_ell": 2,
      "frob_det_mod_ell": 2,
      "frob_matrix_mod_ell": [
        [
          0,
          1
        ],
        [
          1,
          2
        ]
      ]
    },
    {
      "p": 181,
      "a_p": -10,
      "reduction_type": 0,
      "p_divides_N": false,
      "frobenius_angle": -0.3716470731235832,
      "frob_trace_mod_ell": 2,
      "frob_det_mod_ell": 1,
      "frob_matrix_mod_ell": [
        [
          1,
          1
        ],
        [
          0,
          1
        ]
      ]
    },
    {
      "p": 191,
      "a_p": 16,
      "reduction_type": 0,
      "p_divides_N": false,
      "frobenius_angle": 0.5788596842339373,
      "frob_trace_mod_ell": 1,
      "frob_det_mod_ell": 2,
      "frob_matrix_mod_ell": [
        [
          0,
          1
        ],
        [
          1,
          1
        ]
      ]
    },
    {
      "p": 193,
      "a_p": 2,
      "reduction_type": 0,
      "p_divides_N": false,
      "frobenius_angle": 0.07198157507486945,
      "frob_trace_mod_ell": 2,
      "frob_det_mod_ell": 1,
      "frob_matrix_mod_ell": [
        [
          1,
          1
        ],
        [
          0,
          1
        ]
      ]
    },
    {
      "p": 197,
      "a_p": 6,
      "reduction_type": 0,
      "p_divides_N": false,
      "frobenius_angle": 0.21374114996372895,
      "frob_trace_mod_ell": 0,
      "frob_det_mod_ell": 2,
      "frob_matrix_mod_ell": [
        [
          2,
          0
        ],
        [
          0,
          1
        ]
      ]
    },
    {
      "p": 199,
      "a_p": -8,
      "reduction_type": 0,
      "p_divides_N": false,
      "frobenius_angle": -0.2835524820033343,
      "frob_trace_mod_ell": 1,
      "frob_det_mod_ell": 1,
      "frob_matrix_mod_ell": [
        [
          2,
          1
        ],
        [
          0,
          2
        ]
      ]
    }
  ],
  "a_p_list": [
    [
      2,
      -1
    ],
    [
      3,
      -1
    ],
    [
      5,
      1
    ],
    [
      7,
      0
    ],
    [
      11,
      -4
    ],
    [
      13,
      -2
    ],
    [
      17,
      2
    ],
    [
      19,
      4
    ],
    [
      23,
      0
    ],
    [
      29,
      -2
    ],
    [
      31,
      0
    ],
    [
      37,
      -10
    ],
    [
      41,
      10
    ],
    [
      43,
      4
    ],
    [
      47,
      8
    ],
    [
      53,
      -10
    ],
    [
      59,
      -4
    ],
    [
      61,
      -2
    ],
    [
      67,
      12
    ],
    [
      71,
      -8
    ],
    [
      73,
      10
    ],
    [
      79,
      0
    ],
    [
      83,
      12
    ],
    [
      89,
      -6
    ],
    [
      97,
      2
    ],
    [
      101,
      6
    ],
    [
      103,
      -16
    ],
    [
      107,
      -12
    ],
    [
      109,
      14
    ],
    [
      113,
      2
    ],
    [
      127,
      -8
    ],
    [
      131,
      -12
    ],
    [
      137,
      -6
    ],
    [
      139,
      -4
    ],
    [
      149,
      22
    ],
    [
      151,
      -8
    ],
    [
      157,
      14
    ],
    [
      163,
      -4
    ],
    [
      167,
      0
    ],
    [
      173,
      -18
    ],
    [
      179,
      20
    ],
    [
      181,
      -10
    ],
    [
      191,
      16
    ],
    [
      193,
      2
    ],
    [
      197,
      6
    ],
    [
      199,
      -8
    ]
  ],
  "description": "rank 0, conductor 15"
}