{
  "contract_name": "run_packet",
  "contract_version": "v1",
  "run_id": "run_2026_04_04_smoke",
  "created_at_utc": "2026-04-04T05:53:58Z",
  "root_node_id": "node_root",
  "task": {
    "raw_task_text": "Design the backend and build the frontend and validate the feature.",
    "task_source": "manual_cli",
    "constraints": [],
    "success_criteria": [],
    "attachment_refs": []
  },
  "run_level_variables": {
    "model": "deterministic-local-v1",
    "injected_prompt_profile": "default-builder",
    "context_policy": "minimal",
    "workflow_structure": "sequential_parent_review",
    "verification_policy": "light",
    "tool_policy": "none",
    "budget_policy": {
      "max_depth": 1,
      "max_helpers_per_node": 3
    },
    "routing_policy": "return_to_creator",
    "recovery_policy": "report_problem"
  },
  "top_level_context": {
    "context_refs": []
  },
  "root_setup": {
    "root_input_summary": "Design the backend and build the frontend and validate the feature.",
    "notes": []
  }
}
