{
  "contract_name": "final_output",
  "contract_version": "v1",
  "run_id": "atlas-derived-A2-unruh-de-sitter-temperature-ratio-mond-interpolation__gemma426b_execute_probe__run_2026_04_06_071427",
  "created_at_utc": "2026-04-06T07:14:32Z",
  "source_node_id": "node_root",
  "source_node_record_ref": "nodes/node_root/node_record.json",
  "action_type": "report_success",
  "terminal_result_destination": "final_output",
  "result": {
    "result_type": "algebraic_identity",
    "content": "FINAL_ANSWER: 1/\\mu(a)\n\nJUSTIFICATION: In the context of MOND-inspired cosmological models or modified gravity theories where the Unruh temperature is modified by a de Sitter background or an interpolation function $\\mu(a)$, the standard Unruh temperature $T_U(a) = \\frac{\\hbar a}{2\\pi c k_B}$ is modified to $T_{dS}(a) = \\frac{\\hbar a_{eff}}{2\\pi c k_B}$. In MOND, the effective acceleration $a$ is related to the physical acceleration $a_0$ via the interpolation function $\\mu(a/a_0)a = a_0$ (or similar relations depending on the specific formulation). When considering the ratio of the standard Unruh temperature to the modified temperature in these frameworks, the ratio scales inversely with the interpolation function $\\mu(a)$, such that $T_U(a)/T_{dS}(a) = 1/\\mu(a)$.",
    "attachment_refs": []
  }
}
